CoreAprsClient/CoreAprsClient.py
CoreAprsClient/__init__.py
CoreAprsClient/_version.py
CoreAprsClient/client_aprs_communication.py
CoreAprsClient/client_aprsobject.py
CoreAprsClient/client_configuration.py
CoreAprsClient/client_configuration_schema.py
CoreAprsClient/client_expdict.py
CoreAprsClient/client_logger.py
CoreAprsClient/client_message_counter.py
CoreAprsClient/client_return_codes.py
CoreAprsClient/client_shared.py
CoreAprsClient/client_utils.py
core_aprs_client-0.93.dist-info/licenses/LICENSE
core_aprs_client-0.93.dist-info/METADATA
core_aprs_client-0.93.dist-info/WHEEL
core_aprs_client-0.93.dist-info/top_level.txt
core_aprs_client-0.93.dist-info/RECORD
