Metadata-Version: 2.4
Name: core-aprs-client
Version: 0.93
Summary: Extensible APRS bot framework with dupe detection, beacon/bulletin support and other nice features. Just add your custom APRS bot functions - the APRS bot framework will take care of the rest.
Home-page: https://github.com/joergschultzelutter/core-aprs-client
Author: Joerg Schultze-Lutter
Author-email: joerg.schultze.lutter@gmail.com
License: GNU General Public License v3 (GPLv3)
Keywords: Ham Radio,Amateur Radio,APRS
Classifier: Intended Audience :: Developers
Classifier: Programming Language :: Python
Classifier: Programming Language :: Python :: 3
Classifier: Topic :: Software Development
Classifier: Operating System :: OS Independent
Classifier: Development Status :: 5 - Production/Stable
License-File: LICENSE
Requires-Dist: aprslib>=0.7.2
Requires-Dist: apprise>=1.9.4
Requires-Dist: expiringdict>=1.2.2
Requires-Dist: unidecode>=1.4.0
Requires-Dist: apscheduler>=3.11.0
Dynamic: author
Dynamic: author-email
Dynamic: classifier
Dynamic: description
Dynamic: description-content-type
Dynamic: home-page
Dynamic: keywords
Dynamic: license
Dynamic: license-file
Dynamic: requires-dist
Dynamic: summary
